iautolib/__init__.py
iautolib/__main__.py
iautolib/clickFinder.py
iautolib/ilib.py
iautolib/photo_rc.py
iautolib/icons/browse.png
iautolib/icons/code.png
iautolib/icons/copy.png
iautolib/icons/home.png
iautolib/icons/pic.png
iautolib/icons/settings.png
iautolib/themes/classic.css
iautolib/themes/darkblue.css
iautolib/themes/qdark.css
iautolib/themes/waitimage.ui
iautolib-1.0.3.dist-info/LICENSE
iautolib-1.0.3.dist-info/METADATA
iautolib-1.0.3.dist-info/WHEEL
iautolib-1.0.3.dist-info/entry_points.txt
iautolib-1.0.3.dist-info/top_level.txt
iautolib-1.0.3.dist-info/RECORD
