Metadata-Version: 2.1
Name: iautolib
Version: 1.0.3
Summary: This is an Intelligent Automation Library
Home-page: https://github.com/redkad/iautolib
Author: Patrick Adu-Amankwah
Author-email: p.a.amankwah@gmail.com
License: MIT
Platform: UNKNOWN
Classifier: License :: OSI Approved :: MIT License
Classifier: Programming Language :: Python :: 3.6
Classifier: Programming Language :: Python :: 3.7
Classifier: Programming Language :: Python :: 3.8
Classifier: Programming Language :: Python :: 3.9
Requires-Dist: numpy
Requires-Dist: selenium
Requires-Dist: opencv-python
Requires-Dist: pyautogui
Requires-Dist: keyboard
Requires-Dist: pandas
Requires-Dist: requests
Requires-Dist: clipboard
Requires-Dist: tk
Requires-Dist: pywin32
